projectaile/__init__.py
projectaile/config/__init__.py
projectaile/config/base_config.yaml
projectaile/config/config.py
projectaile/config/dtypes.py
projectaile/data/__init__.py
projectaile/data/extractors/__init__.py
projectaile/data/extractors/csv_extractor.py
projectaile/data/extractors/extractor_utils.py
projectaile/data/feeder.py
projectaile/data/loader.py
projectaile/data/loaders/__init__.py
projectaile/data/loaders/image_loader.py
projectaile/engine/__init__.py
projectaile/engine/engine.py
projectaile/loggers/__init__.py
projectaile/loggers/logger.py
projectaile/model/__init__.py
projectaile/model/model.py
projectaile/pipelines/__init__.py
projectaile/pipelines/augmentations/__init__.py
projectaile/pipelines/augmentations/augmentation.py
projectaile/pipelines/data_pipeline.py
projectaile/pipelines/model_pipeline.py
projectaile/pipelines/pipeline.py
projectaile/pipelines/preprocesses/__init__.py
projectaile/pipelines/preprocesses/image.py
projectaile/pipelines/preprocesses/preprocess.py
projectaile/savers/__init__.py
projectaile/savers/saver.py
projectaile/utils/__init__.py
projectaile/utils/base_class.py
projectaile/utils/container.py
projectaile/utils/create_project.py
projectaile/utils/exception_handler.py
projectaile/utils/exceptions.py
projectaile/utils/validator.py
projectaile/version.py
projectaile-0.0.1.dist-info/LICENSE
projectaile-0.0.1.dist-info/WHEEL
projectaile-0.0.1.dist-info/METADATA
projectaile-0.0.1.dist-info/RECORD
