Metadata-Version: 2.1
Name: projectaile
Version: 0.0.1
Summary: A framework agnostic architecture and utility library for all machine learning and deep learning projects providing an abstract and easy to use but still very configurable API.
License: MIT
Author: abtExp
Author-email: abt.exp@gmail.com
Requires-Python: >=3.6,<4.0
Classifier: License :: OSI Approved :: MIT License
Classifier: Programming Language :: Python :: 3
Classifier: Programming Language :: Python :: 3.10
Classifier: Programming Language :: Python :: 3.6
Classifier: Programming Language :: Python :: 3.7
Classifier: Programming Language :: Python :: 3.8
Classifier: Programming Language :: Python :: 3.9
